NanostructureUCPH/__init__.py
NanostructureUCPH/CifConverter/__init__.py
NanostructureUCPH/CifConverter/cifConverter.py
NanostructureUCPH-0.0.1.dist-info/LICENSE
NanostructureUCPH-0.0.1.dist-info/METADATA
NanostructureUCPH-0.0.1.dist-info/WHEEL
NanostructureUCPH-0.0.1.dist-info/top_level.txt
NanostructureUCPH-0.0.1.dist-info/RECORD
