Metadata-Version: 2.1
Name: NanostructureUCPH
Version: 0.0.1
Summary: Pakage for analyzing nanostructures
Home-page: https://github.com/EmilSkaaning/NanostructureUCPH
Author: Emil Thyge Skaaning Kjaer
Author-email: rsz113@alumni.ku.dk
License: MIT
Keywords: structure science
Platform: UNKNOWN
Classifier: Development Status :: 2 - Pre-Alpha
Classifier: Intended Audience :: Science/Research
Classifier: License :: OSI Approved :: MIT License
Classifier: Programming Language :: Python :: 2.7
Classifier: Topic :: Scientific/Engineering :: Chemistry
Requires-Dist: numpy
